politikontroller_py/__init__.py
politikontroller_py/cli.py
politikontroller_py/client.py
politikontroller_py/constants.py
politikontroller_py/exceptions.py
politikontroller_py/models/__init__.py
politikontroller_py/models/account.py
politikontroller_py/models/api.py
politikontroller_py/models/common.py
politikontroller_py/py.typed
politikontroller_py/utils.py
politikontroller_py/version.py
politikontroller_py-3.3.2.dist-info/LICENSE
politikontroller_py-3.3.2.dist-info/METADATA
politikontroller_py-3.3.2.dist-info/WHEEL
politikontroller_py-3.3.2.dist-info/entry_points.txt
politikontroller_py-3.3.2.dist-info/RECORD
