Metadata-Version: 2.1
Name: politikontroller-py
Version: 3.3.2
Summary: Unofficial client for politikontroller.no
License: MIT
Author: Bendik R. Brenne
Author-email: bendik@konstant.no
Requires-Python: >=3.10,<3.13
Classifier: License :: OSI Approved :: MIT License
Classifier: Programming Language :: Python :: 3
Classifier: Programming Language :: Python :: 3.10
Classifier: Programming Language :: Python :: 3.11
Classifier: Programming Language :: Python :: 3.12
Requires-Dist: aiohttp (>=3.11,<4.0)
Requires-Dist: anyio (==4.*)
Requires-Dist: async-timeout (>=4.0.3,<5.0.0)
Requires-Dist: asyncclick (==8.*)
Requires-Dist: geojson (>=3.1.0,<4.0.0)
Requires-Dist: mashumaro[orjson] (>=3.13.1,<4.0.0)
Requires-Dist: pycryptodome (>=3.21.0,<4.0.0)
Requires-Dist: tabulate (==0.9.*)
